pkg_dvp_mathematique/__init__.py
pkg_dvp_mathematique/operations_avances.py
pkg_dvp_mathematique/operations_basiques.py
pkg_dvp_mathematique-0.0.5.dist-info/DESCRIPTION.rst
pkg_dvp_mathematique-0.0.5.dist-info/METADATA
pkg_dvp_mathematique-0.0.5.dist-info/RECORD
pkg_dvp_mathematique-0.0.5.dist-info/WHEEL
pkg_dvp_mathematique-0.0.5.dist-info/metadata.json
pkg_dvp_mathematique-0.0.5.dist-info/top_level.txt
test_mathematique/__init__.py
test_mathematique/tests_avances.py
test_mathematique/tests_basiques.py
