Metadata-Version: 2.0
Name: pkg-dvp-mathematique
Version: 0.0.5
Summary: demonstration de creation d'un package Python
Home-page: http://www.developpez.com
Author: dvp
Author-email: dvp@dvp.com
License: GPL V3
Keywords: dvp developpez.com deusyss package Python
Platform: UNKNOWN
Classifier: Topic :: Education
Classifier: Topic :: Documentation
